kfst/__init__.py
kfst/convert.py
kfst/symbols.py
kfst/transducer.py
kfst-4.2.3.dist-info/licenses/LICENSE
kfst_py/__init__.py
kfst_py/symbols.py
kfst_py/transducer.py
kfst_py/format/att.py
kfst_py/format/kfst.py
kfst-4.2.3.dist-info/METADATA
kfst-4.2.3.dist-info/WHEEL
kfst-4.2.3.dist-info/top_level.txt
kfst-4.2.3.dist-info/RECORD
