Metadata-Version: 2.4
Name: kfst
Version: 4.2.3
Summary: A pure-python when needed, transparently natively accelerated if available, finite state transducer library
Home-page: https://github.com/fergusq/fst-python
Author: Iikka Hauhio, Théo Salmenkivi-Friberg
Author-email: iikka.hauhio@helsinki.fi, theo.friberg@helsinki.fi
License: GNU LGPLv3 or later
Project-URL: Bug Tracker, https://github.com/fergusq/fst-python/issues
Classifier: License :: OSI Approved :: GNU Lesser General Public License v3 or later (LGPLv3+)
Classifier: Programming Language :: Python
Classifier: Programming Language :: Python :: 3
Requires-Python: >=3.8
License-File: LICENSE
Requires-Dist: immutables
Dynamic: license-file
